{"type":"module","coordinates":{"identifier":"androidx.fragment:fragment-ktx","resolvedVersion":"1.6.0","gradleVariantIdentification":{"capabilities":["androidx.fragment:fragment-ktx"],"attributes":{}}},"capabilities":{"com.autonomousapps.model.InferredCapability":{"type":"inferred","isCompileOnlyAnnotations":false},"com.autonomousapps.model.ClassCapability":{"type":"class","classes":["androidx.fragment.app.FragmentKt","androidx.fragment.app.FragmentManagerKt","androidx.fragment.app.FragmentTransactionKt","androidx.fragment.app.FragmentViewModelLazyKt","androidx.fragment.app.FragmentViewModelLazyKt$activityViewModels$1","androidx.fragment.app.FragmentViewModelLazyKt$activityViewModels$2","androidx.fragment.app.FragmentViewModelLazyKt$activityViewModels$3","androidx.fragment.app.FragmentViewModelLazyKt$activityViewModels$4","androidx.fragment.app.FragmentViewModelLazyKt$activityViewModels$5","androidx.fragment.app.FragmentViewModelLazyKt$activityViewModels$6","androidx.fragment.app.FragmentViewModelLazyKt$createViewModelLazy$1","androidx.fragment.app.FragmentViewModelLazyKt$createViewModelLazy$2","androidx.fragment.app.FragmentViewModelLazyKt$createViewModelLazy$factoryPromise$1","androidx.fragment.app.FragmentViewModelLazyKt$viewModels$1","androidx.fragment.app.FragmentViewModelLazyKt$viewModels$2","androidx.fragment.app.FragmentViewModelLazyKt$viewModels$3","androidx.fragment.app.FragmentViewModelLazyKt$viewModels$4","androidx.fragment.app.FragmentViewModelLazyKt$viewModels$5","androidx.fragment.app.FragmentViewModelLazyKt$viewModels$6","androidx.fragment.app.FragmentViewModelLazyKt$viewModels$7","androidx.fragment.app.FragmentViewModelLazyKt$viewModels$8","androidx.fragment.app.FragmentViewModelLazyKt$viewModels$owner$2","androidx.fragment.app.FragmentViewModelLazyKt$viewModels$owner$4","androidx.fragment.app.ViewKt","androidx.fragment.ktx.R"]},"com.autonomousapps.model.InlineMemberCapability":{"type":"inline","inlineMembers":[{"packageName":"androidx.fragment.app","inlineMembers":["activityViewModels","viewModels"]},{"packageName":"androidx.fragment.app","inlineMembers":["add","replace"]},{"packageName":"androidx.fragment.app","inlineMembers":["commit","commitNow","transaction"]}]},"com.autonomousapps.model.AndroidManifestCapability":{"type":"manifest","componentMap":{}},"com.autonomousapps.model.AndroidResCapability":{"type":"res","rImport":"androidx.fragment.ktx.R","lines":[]}},"files":["/home/toor/.gradle/caches/transforms-3/8085d126e7498e1dc968948f2dd24dd1/transformed/jetified-fragment-ktx-1.6.0-api.jar"]}