{"type":"module","coordinates":{"identifier":"com.google.guava:listenablefuture","resolvedVersion":"1.0","gradleVariantIdentification":{"capabilities":["com.google.guava:listenablefuture"],"attributes":{}}},"capabilities":{"com.autonomousapps.model.InferredCapability":{"type":"inferred","isCompileOnlyAnnotations":false},"com.autonomousapps.model.ClassCapability":{"type":"class","classes":["com.google.common.util.concurrent.ListenableFuture"]}},"files":["/home/toor/.gradle/caches/transforms-3/b9786954d3c24c0a5c215ce7d5e6887c/transformed/jetified-listenablefuture-1.0.jar"]}